boa/__init__.py
boa/_version.py
boa/cpymadtools/__init__.py
boa/cpymadtools/coupling.py
boa/cpymadtools/matching.py
boa/cpymadtools/ptc.py
boa/cpymadtools/track.py
boa/cpymadtools/twiss.py
boa/cpymadtools/utils.py
boa-0.0.5.dist-info/LICENSE
boa-0.0.5.dist-info/METADATA
boa-0.0.5.dist-info/WHEEL
boa-0.0.5.dist-info/top_level.txt
boa-0.0.5.dist-info/RECORD
